Metadata-Version: 2.1
Name: TexGeneratorStepanovItmoMhsYandex
Version: 1.0.0
Summary: Latex table and img generator library
Home-page: UNKNOWN
Author-email: nik-stepanov-2001@bk.ru
License: UNKNOWN
Platform: UNKNOWN
